zbar.cp38-win_amd64.pyd
zbar_helper/__init__.py
zbar_helper/utils.py
zbar_lite-0.23.93.dist-info/LICENSE
zbar_lite-0.23.93.dist-info/METADATA
zbar_lite-0.23.93.dist-info/WHEEL
zbar_lite-0.23.93.dist-info/top_level.txt
zbar_lite-0.23.93.dist-info/RECORD
