Metadata-Version: 2.1
Name: zbar-lite
Version: 0.23.93
Summary: zbar lite package only support scan image and recognize barcode
Home-page: https://github.com/wqh17101/zbar_lite
Author: Qinghua Wang
Author-email: 597935261@qq.com
License: MIT
Platform: UNKNOWN
